{
	"description": "项目配置文件",
	"packOptions": {
		"ignore": []
	},
	"setting": {
		"urlCheck": false,
		"es6": true,
		"postcss": true,
		"minified": true,
		"newFeature": true,
		"autoAudits": false
	},
	"compileType": "miniprogram",
	"libVersion": "2.6.2",
	"appid": "wx139c8bb378458c37",
	"projectname": "%E6%98%8E%E5%A4%A9%E4%BD%A0%E5%A5%BD",
	"debugOptions": {
		"hidedInDevtools": []
	},
	"isGameTourist": false,
	"condition": {
		"search": {
			"current": -1,
			"list": []
		},
		"conversation": {
			"current": -1,
			"list": []
		},
		"game": {
			"currentL": -1,
			"list": []
		},
		"miniprogram": {
			"current": -1,
			"list": []
		}
	}
}